sql_pydb/Cell.py
sql_pydb/Column.py
sql_pydb/Database.py
sql_pydb/Table.py
sql_pydb/TableCommands.py
sql_pydb/__init__.py
sql_pydb-0.6.0.dist-info/METADATA
sql_pydb-0.6.0.dist-info/WHEEL
sql_pydb-0.6.0.dist-info/top_level.txt
sql_pydb-0.6.0.dist-info/RECORD
